dotflow/__init__.py
dotflow/api/__init__.py
dotflow/api/dsl.py
dotflow/api/mixins.py
dotflow/api/natural.py
dotflow/api/pythonic.py
dotflow/cli/__init__.py
dotflow/cli/main.py
dotflow/core/__init__.py
dotflow/core/interpreter.py
dotflow/core/models.py
dotflow/core/renderer.py
dotflow/core/styles.py
dotflow/core/themes.py
dotflow/exporters/__init__.py
dotflow/exporters/base.py
dotflow/exporters/dot.py
dotflow/exporters/image.py
dotflow/tests/__init__.py
dotflow/tests/test_api.py
dotflow/tests/test_cli.py
dotflow/tests/test_core.py
dotflow/tests/test_expoters.py
dotflow/tests/test_utils.py
dotflow/tests/__pycache__/__init__.cpython-313.pyc
dotflow/tests/__pycache__/test_cli.cpython-313-pytest-8.3.5.pyc
dotflow/tests/__pycache__/test_core.cpython-313-pytest-8.3.5.pyc
dotflow/tests/__pycache__/test_core.cpython-313.pyc
dotflow/utils/__init__.py
dotflow/utils/colors.py
dotflow/utils/exceptions.py
dotflow/utils/screen.py
dotflow/utils/validators.py
dotflow_examples/core.py
dotflow_py-0.1.0.dist-info/licenses/LICENSE
dotflow_py-0.1.0.dist-info/METADATA
dotflow_py-0.1.0.dist-info/WHEEL
dotflow_py-0.1.0.dist-info/entry_points.txt
dotflow_py-0.1.0.dist-info/top_level.txt
dotflow_py-0.1.0.dist-info/RECORD
