Metadata-Version: 2.4
Name: dotflow-py
Version: 0.1.0
Summary: A Python-based DOT language interpreter with multiple API styles
Home-page: https://pypi.org/project/dotflow-py/
Author: wambua
Author-email: swskye17@gmail.com
License: MIT
Keywords: graphviz,dot,diagram,flowchart
Classifier: Environment :: Console
Classifier: Natural Language :: English
Classifier: Operating System :: OS Independent
Classifier: Programming Language :: Python
Classifier: Programming Language :: Python :: 3 :: Only
Classifier: Programming Language :: Python :: 3.12
Classifier: Programming Language :: Python :: 3.13
Requires-Python: >=3.12
License-File: LICENSE
Requires-Dist: setuptools
Requires-Dist: wheel
Requires-Dist: argparse
Dynamic: author
Dynamic: author-email
Dynamic: classifier
Dynamic: description
Dynamic: description-content-type
Dynamic: home-page
Dynamic: keywords
Dynamic: license
Dynamic: license-file
Dynamic: requires-dist
Dynamic: requires-python
Dynamic: summary
